{
	"version": 1,
	"collections": [
		{
			"id": "0ffe227a-a9ab-ac34-9e7c-5ab70e5156a1",
			"name": "sanzone",
			"description": "",
			"order": [],
			"folders": [
				{
					"id": "ea1fe0ae-e0f3-cea7-4b89-02e377a74489",
					"name": "SanzoneImageController",
					"description": "",
					"write": true,
					"order": [
						"372e4c52-dec4-1a7e-15c0-09969a00b3d8",
						"5e11fe80-dfbb-ef9d-a6ce-c4c01373c53f",
						"859e9b8b-163b-6a36-0d21-047e47bc32ee",
						"82291b4b-7299-d77b-a5c8-f7df850e78a6",
						"bec3b8e7-7e02-6c3b-4f12-e19257e9b7b6",
						"13908988-6f2b-56a7-b541-aa5b336f7abe",
						"d1538a4d-4efb-a3a6-140e-6c661101208e",
						"1b64c6be-ca4c-81d9-3bc4-de3f5b1c3427",
						"05da6b04-950d-9cee-5c59-576254f88d67"
					],
					"collection": "0ffe227a-a9ab-ac34-9e7c-5ab70e5156a1",
					"owner": 0,
					"collection_id": "0ffe227a-a9ab-ac34-9e7c-5ab70e5156a1"
				}
			],
			"timestamp": 1473710197157,
			"synced": false,
			"remote_id": 0,
			"owner": 0,
			"sharedWithTeam": false,
			"subscribed": false,
			"remoteLink": "",
			"remoteLinkUpdatedAt": null,
			"public": false,
			"createdAt": 1473710197157,
			"updatedAt": 1479140504112,
			"write": true,
			"published": false,
			"favorite": false,
			"permissions": {},
			"syncedPermissions": {},
			"requests": [
				{
					"id": "05da6b04-950d-9cee-5c59-576254f88d67",
					"headers": "Content-Type: application/json\n",
					"url": "http://localhost:8081/v1/summary/opencv",
					"preRequestScript": null,
					"pathVariables": {},
					"method": "POST",
					"data": "{\r\n \"sectors\": [\r\n  {\r\n   \"latitude\": 53.870166,\r\n   \"longitude\": 27.567111,\r\n   \"azimuth\": 10,\r\n   \"antenna\": {\r\n    \"power\": 90,\r\n    \"gain\": 18.21,\r\n    \"tractLost\": -1.6,\r\n    \"earthFactor\": 1,\r\n    \"diagramWidthHalfPower\": 45\r\n   }\r\n  },\r\n  {\r\n   \"latitude\": 53.870166,\r\n   \"longitude\": 27.567111,\r\n   \"azimuth\": 110,\r\n   \"antenna\": {\r\n    \"power\": 150,\r\n    \"gain\": 15.21,\r\n    \"tractLost\": -1.6,\r\n    \"earthFactor\": 1,\r\n    \"diagramWidthHalfPower\": 35\r\n   }\r\n  },\r\n  {\r\n   \"latitude\": 53.870166,\r\n   \"longitude\": 27.567111,\r\n   \"azimuth\": 270,\r\n   \"antenna\": {\r\n    \"power\": 100,\r\n    \"gain\": 20.21,\r\n    \"tractLost\": -1.6,\r\n    \"earthFactor\": 1,\r\n    \"diagramWidthHalfPower\": 45\r\n   }\r\n  }\r\n ]\r\n}",
					"dataMode": "raw",
					"version": 2,
					"tests": null,
					"currentHelper": "normal",
					"helperAttributes": {},
					"time": 1478950339592,
					"name": "createSummarySanzoneImage_4_sectors_v4",
					"description": "",
					"collectionId": "0ffe227a-a9ab-ac34-9e7c-5ab70e5156a1",
					"responses": []
				},
				{
					"id": "13908988-6f2b-56a7-b541-aa5b336f7abe",
					"headers": "Content-Type: application/json\n",
					"url": "http://localhost:8081/v1/summary/opencv",
					"preRequestScript": null,
					"pathVariables": {},
					"method": "POST",
					"data": "{\n\t\"sectors\": [\n\t\t{\n\t\t\t\"latitude\": 53.870166,\n\t\t\t\"longitude\": 27.567111,\n\t\t\t\"azimuth\": 0,\n\t\t\t\"antenna\": {\n\t\t\t\t\"power\": 60,\n\t\t\t\t\"gain\": 15.21,\n\t\t\t\t\"tractLost\": -1.6,\n\t\t\t\t\"earthFactor\": 1,\n\t\t\t\t\"diagramWidthHalfPower\": 65\n\t\t\t}\n\t\t},\n\t\t{\n\t\t\t\"latitude\": 53.870166,\n\t\t\t\"longitude\": 27.567111,\n\t\t\t\"azimuth\": 90,\n\t\t\t\"antenna\": {\n\t\t\t\t\"power\": 60,\n\t\t\t\t\"gain\": 15.21,\n\t\t\t\t\"tractLost\": -1.6,\n\t\t\t\t\"earthFactor\": 1,\n\t\t\t\t\"diagramWidthHalfPower\": 65\n\t\t\t}\n\t\t},\n\t\t{\n\t\t\t\"latitude\": 53.870166,\n\t\t\t\"longitude\": 27.567111,\n\t\t\t\"azimuth\": 180,\n\t\t\t\"antenna\": {\n\t\t\t\t\"power\": 60,\n\t\t\t\t\"gain\": 15.21,\n\t\t\t\t\"tractLost\": -1.6,\n\t\t\t\t\"earthFactor\": 1,\n\t\t\t\t\"diagramWidthHalfPower\": 65\n\t\t\t}\n\t\t},\n\t\t\t{\n\t\t\t\"latitude\": 53.870166,\n\t\t\t\"longitude\": 27.567111,\n\t\t\t\"azimuth\": 270,\n\t\t\t\"antenna\": {\n\t\t\t\t\"power\": 60,\n\t\t\t\t\"gain\": 15.21,\n\t\t\t\t\"tractLost\": -1.6,\n\t\t\t\t\"earthFactor\": 1,\n\t\t\t\t\"diagramWidthHalfPower\": 65\n\t\t\t}\n\t\t}\n\t]\n}",
					"dataMode": "raw",
					"version": 2,
					"tests": null,
					"currentHelper": "normal",
					"helperAttributes": {},
					"time": 1478599173445,
					"name": "createSummarySanzoneImage_4_sectors_v1",
					"description": "",
					"collectionId": "0ffe227a-a9ab-ac34-9e7c-5ab70e5156a1",
					"responses": [],
					"folder": "ea1fe0ae-e0f3-cea7-4b89-02e377a74489"
				},
				{
					"id": "1b64c6be-ca4c-81d9-3bc4-de3f5b1c3427",
					"headers": "Content-Type: application/json\n",
					"url": "http://localhost:8081/v1/summary/opencv",
					"preRequestScript": null,
					"pathVariables": {},
					"method": "POST",
					"data": "{\r\n \"sectors\": [\r\n  {\r\n   \"latitude\": 53.870166,\r\n   \"longitude\": 27.567111,\r\n   \"azimuth\": 30,\r\n   \"antenna\": {\r\n    \"power\": 60,\r\n    \"gain\": 11.21,\r\n    \"tractLost\": -1.6,\r\n    \"earthFactor\": 1,\r\n    \"diagramWidthHalfPower\": 65\r\n   }\r\n  },\r\n  {\r\n   \"latitude\": 53.870166,\r\n   \"longitude\": 27.567111,\r\n   \"azimuth\": 130,\r\n   \"antenna\": {\r\n    \"power\": 150,\r\n    \"gain\": 15.21,\r\n    \"tractLost\": -1.6,\r\n    \"earthFactor\": 1,\r\n    \"diagramWidthHalfPower\": 65\r\n   }\r\n  },\r\n  {\r\n   \"latitude\": 53.870166,\r\n   \"longitude\": 27.567111,\r\n   \"azimuth\": 290,\r\n   \"antenna\": {\r\n    \"power\": 100,\r\n    \"gain\": 5.21,\r\n    \"tractLost\": -1.6,\r\n    \"earthFactor\": 1,\r\n    \"diagramWidthHalfPower\": 45\r\n   }\r\n  }\r\n ]\r\n}",
					"dataMode": "raw",
					"version": 2,
					"tests": null,
					"currentHelper": "normal",
					"helperAttributes": {},
					"time": 1478950321318,
					"name": "createSummarySanzoneImage_4_sectors_v3",
					"description": "",
					"collectionId": "0ffe227a-a9ab-ac34-9e7c-5ab70e5156a1",
					"responses": [],
					"folder": "ea1fe0ae-e0f3-cea7-4b89-02e377a74489"
				},
				{
					"id": "372e4c52-dec4-1a7e-15c0-09969a00b3d8",
					"headers": "Content-Type: application/json\n",
					"url": "http://localhost:8081/v1/sector",
					"preRequestScript": null,
					"pathVariables": {},
					"method": "POST",
					"data": "{\n\t\"sectors\": [\n\t\t{\n\t\t\t\"latitude\": 53.870166,\n\t\t\t\"longitude\": 27.567111,\n\t\t\t\"azimuth\": 50,\n\t\t\t\"antenna\": {\n\t\t\t\t\"power\": 60,\n\t\t\t\t\"gain\": 15.21,\n\t\t\t\t\"tractLost\": -1.6,\n\t\t\t\t\"earthFactor\": 1,\n\t\t\t\t\"diagramWidthHalfPower\": 65\n\t\t\t}\n\t\t}\n\t]\n}",
					"dataMode": "raw",
					"version": 2,
					"tests": null,
					"currentHelper": "normal",
					"helperAttributes": {},
					"time": 1475498968343,
					"name": "createSectorSanzoneImage",
					"description": "",
					"collectionId": "0ffe227a-a9ab-ac34-9e7c-5ab70e5156a1",
					"responses": []
				},
				{
					"id": "5e11fe80-dfbb-ef9d-a6ce-c4c01373c53f",
					"headers": "Content-Type: application/json\n",
					"url": "http://localhost:8081/v1/summary/pixels",
					"preRequestScript": null,
					"pathVariables": {},
					"method": "POST",
					"data": "{\n\t\"sectors\": [\n\t\t{\n\t\t\t\"latitude\": 53.870166,\n\t\t\t\"longitude\": 27.567111,\n\t\t\t\"azimuth\": 50,\n\t\t\t\"antenna\": {\n\t\t\t\t\"power\": 60,\n\t\t\t\t\"gain\": 15.21,\n\t\t\t\t\"tractLost\": -1.6,\n\t\t\t\t\"earthFactor\": 1,\n\t\t\t\t\"diagramWidthHalfPower\": 65\n\t\t\t}\n\t\t},\n\t\t{\n\t\t\t\"latitude\": 53.870166,\n\t\t\t\"longitude\": 27.567111,\n\t\t\t\"azimuth\": 175,\n\t\t\t\"antenna\": {\n\t\t\t\t\"power\": 60,\n\t\t\t\t\"gain\": 15.21,\n\t\t\t\t\"tractLost\": -1.6,\n\t\t\t\t\"earthFactor\": 1,\n\t\t\t\t\"diagramWidthHalfPower\": 65\n\t\t\t}\n\t\t},\n\t\t{\n\t\t\t\"latitude\": 53.870166,\n\t\t\t\"longitude\": 27.567111,\n\t\t\t\"azimuth\": 310,\n\t\t\t\"antenna\": {\n\t\t\t\t\"power\": 60,\n\t\t\t\t\"gain\": 15.21,\n\t\t\t\t\"tractLost\": -1.6,\n\t\t\t\t\"earthFactor\": 1,\n\t\t\t\t\"diagramWidthHalfPower\": 65\n\t\t\t}\n\t\t}\n\t]\n}",
					"dataMode": "raw",
					"version": 2,
					"tests": null,
					"currentHelper": "normal",
					"helperAttributes": {},
					"time": 1478599069228,
					"name": "createSummarySanzoneImage",
					"description": "",
					"collectionId": "0ffe227a-a9ab-ac34-9e7c-5ab70e5156a1",
					"responses": []
				},
				{
					"id": "82291b4b-7299-d77b-a5c8-f7df850e78a6",
					"headers": "Content-Type: application/json\n",
					"url": "http://localhost:8081/v1/summary/opencv",
					"preRequestScript": null,
					"pathVariables": {},
					"method": "POST",
					"data": "{\n\t\"sectors\": [\n\t\t{\n\t\t\t\"latitude\": 53.870166,\n\t\t\t\"longitude\": 27.567111,\n\t\t\t\"azimuth\": 50,\n\t\t\t\"antenna\": {\n\t\t\t\t\"power\": 60,\n\t\t\t\t\"gain\": 15.21,\n\t\t\t\t\"tractLost\": -1.6,\n\t\t\t\t\"earthFactor\": 1,\n\t\t\t\t\"diagramWidthHalfPower\": 65\n\t\t\t}\n\t\t},\n\t\t{\n\t\t\t\"latitude\": 53.870166,\n\t\t\t\"longitude\": 27.567111,\n\t\t\t\"azimuth\": 175,\n\t\t\t\"antenna\": {\n\t\t\t\t\"power\": 60,\n\t\t\t\t\"gain\": 15.21,\n\t\t\t\t\"tractLost\": -1.6,\n\t\t\t\t\"earthFactor\": 1,\n\t\t\t\t\"diagramWidthHalfPower\": 65\n\t\t\t}\n\t\t},\n\t\t{\n\t\t\t\"latitude\": 53.870166,\n\t\t\t\"longitude\": 27.567111,\n\t\t\t\"azimuth\": 310,\n\t\t\t\"antenna\": {\n\t\t\t\t\"power\": 60,\n\t\t\t\t\"gain\": 15.21,\n\t\t\t\t\"tractLost\": -1.6,\n\t\t\t\t\"earthFactor\": 1,\n\t\t\t\t\"diagramWidthHalfPower\": 65\n\t\t\t}\n\t\t}\n\t]\n}",
					"dataMode": "raw",
					"version": 2,
					"tests": null,
					"currentHelper": "normal",
					"helperAttributes": {},
					"time": 1478596831166,
					"name": "createSummarySanzoneImageWithOpenCV_v1",
					"description": "",
					"collectionId": "0ffe227a-a9ab-ac34-9e7c-5ab70e5156a1",
					"responses": []
				},
				{
					"id": "859e9b8b-163b-6a36-0d21-047e47bc32ee",
					"headers": "Content-Type: application/json\n",
					"url": "http://localhost:8081/v1/summary/blurGaussian",
					"preRequestScript": null,
					"pathVariables": {},
					"method": "POST",
					"data": "{\n\t\"sectors\": [\n\t\t{\n\t\t\t\"latitude\": 53.870166,\n\t\t\t\"longitude\": 27.567111,\n\t\t\t\"azimuth\": 50,\n\t\t\t\"antenna\": {\n\t\t\t\t\"power\": 60,\n\t\t\t\t\"gain\": 15.21,\n\t\t\t\t\"tractLost\": -1.6,\n\t\t\t\t\"earthFactor\": 1,\n\t\t\t\t\"diagramWidthHalfPower\": 65\n\t\t\t}\n\t\t},\n\t\t{\n\t\t\t\"latitude\": 53.870166,\n\t\t\t\"longitude\": 27.567111,\n\t\t\t\"azimuth\": 175,\n\t\t\t\"antenna\": {\n\t\t\t\t\"power\": 60,\n\t\t\t\t\"gain\": 15.21,\n\t\t\t\t\"tractLost\": -1.6,\n\t\t\t\t\"earthFactor\": 1,\n\t\t\t\t\"diagramWidthHalfPower\": 65\n\t\t\t}\n\t\t},\n\t\t{\n\t\t\t\"latitude\": 53.870166,\n\t\t\t\"longitude\": 27.567111,\n\t\t\t\"azimuth\": 310,\n\t\t\t\"antenna\": {\n\t\t\t\t\"power\": 60,\n\t\t\t\t\"gain\": 15.21,\n\t\t\t\t\"tractLost\": -1.6,\n\t\t\t\t\"earthFactor\": 1,\n\t\t\t\t\"diagramWidthHalfPower\": 65\n\t\t\t}\n\t\t}\n\t]\n}",
					"dataMode": "raw",
					"version": 2,
					"tests": null,
					"currentHelper": "normal",
					"helperAttributes": {},
					"time": 1477933719158,
					"name": "createSummarySanzoneImageWithColorProcessing",
					"description": "",
					"collectionId": "0ffe227a-a9ab-ac34-9e7c-5ab70e5156a1",
					"responses": []
				},
				{
					"id": "bec3b8e7-7e02-6c3b-4f12-e19257e9b7b6",
					"headers": "Content-Type: application/json\n",
					"url": "http://localhost:8081/v1/summary/opencv",
					"preRequestScript": null,
					"pathVariables": {},
					"method": "POST",
					"data": "{\n\t\"sectors\": [\n\t\t{\n\t\t\t\"latitude\": 53.870156,\n\t\t\t\"longitude\": 27.567181,\n\t\t\t\"azimuth\": 50,\n\t\t\t\"antenna\": {\n\t\t\t\t\"power\": 60,\n\t\t\t\t\"gain\": 15.21,\n\t\t\t\t\"tractLost\": -1.6,\n\t\t\t\t\"earthFactor\": 1,\n\t\t\t\t\"diagramWidthHalfPower\": 65\n\t\t\t}\n\t\t},\n\t\t{\n\t\t\t\"latitude\": 53.870096,\n\t\t\t\"longitude\": 27.567601,\n\t\t\t\"azimuth\": 175,\n\t\t\t\"antenna\": {\n\t\t\t\t\"power\": 60,\n\t\t\t\t\"gain\": 15.21,\n\t\t\t\t\"tractLost\": -1.6,\n\t\t\t\t\"earthFactor\": 1,\n\t\t\t\t\"diagramWidthHalfPower\": 65\n\t\t\t}\n\t\t},\n\t\t{\n\t\t\t\"latitude\": 53.870027,\n\t\t\t\"longitude\": 27.566731,\n\t\t\t\"azimuth\": 310,\n\t\t\t\"antenna\": {\n\t\t\t\t\"power\": 60,\n\t\t\t\t\"gain\": 15.21,\n\t\t\t\t\"tractLost\": -1.6,\n\t\t\t\t\"earthFactor\": 1,\n\t\t\t\t\"diagramWidthHalfPower\": 65\n\t\t\t}\n\t\t}\n\t]\n}",
					"dataMode": "raw",
					"version": 2,
					"tests": null,
					"currentHelper": "normal",
					"helperAttributes": {},
					"time": 1479141421048,
					"name": "createSummarySanzoneImageWithOpenCV_v2",
					"description": "",
					"collectionId": "0ffe227a-a9ab-ac34-9e7c-5ab70e5156a1",
					"responses": []
				},
				{
					"id": "d1538a4d-4efb-a3a6-140e-6c661101208e",
					"headers": "Content-Type: application/json\n",
					"url": "http://localhost:8081/v1/summary/opencv",
					"preRequestScript": null,
					"pathVariables": {},
					"method": "POST",
					"data": "{\r\n \"sectors\": [\r\n  {\r\n   \"latitude\": 53.870166,\r\n   \"longitude\": 27.567111,\r\n   \"azimuth\": 0,\r\n   \"antenna\": {\r\n    \"power\": 60,\r\n    \"gain\": 15.21,\r\n    \"tractLost\": -1.6,\r\n    \"earthFactor\": 1,\r\n    \"diagramWidthHalfPower\": 65\r\n   }\r\n  },\r\n  {\r\n   \"latitude\": 53.870166,\r\n   \"longitude\": 27.567111,\r\n   \"azimuth\": 90,\r\n   \"antenna\": {\r\n    \"power\": 80,\r\n    \"gain\": 16.21,\r\n    \"tractLost\": -1.6,\r\n    \"earthFactor\": 1,\r\n    \"diagramWidthHalfPower\": 60\r\n   }\r\n  },\r\n  {\r\n   \"latitude\": 53.870166,\r\n   \"longitude\": 27.567111,\r\n   \"azimuth\": 180,\r\n   \"antenna\": {\r\n    \"power\": 100,\r\n    \"gain\": 17.21,\r\n    \"tractLost\": -1.6,\r\n    \"earthFactor\": 1,\r\n    \"diagramWidthHalfPower\": 55\r\n   }\r\n  },\r\n   {\r\n   \"latitude\": 53.870166,\r\n   \"longitude\": 27.567111,\r\n   \"azimuth\": 270,\r\n   \"antenna\": {\r\n    \"power\": 120,\r\n    \"gain\": 18.21,\r\n    \"tractLost\": -1.6,\r\n    \"earthFactor\": 1,\r\n    \"diagramWidthHalfPower\": 50\r\n   }\r\n  }\r\n ]\r\n}",
					"dataMode": "raw",
					"version": 2,
					"tests": null,
					"currentHelper": "normal",
					"helperAttributes": {},
					"time": 1478950292660,
					"name": "createSummarySanzoneImage_4_sectors_v2",
					"description": "",
					"collectionId": "0ffe227a-a9ab-ac34-9e7c-5ab70e5156a1",
					"responses": [],
					"folder": "ea1fe0ae-e0f3-cea7-4b89-02e377a74489"
				}
			]
		}
	],
	"environments": [],
	"headerPresets": [],
	"globals": []
}